{"cameraMode":{"drawMode":0,"name":"Shaded","section":"Shading Mode"},"sceneLighting":true,"audioPlay":false,"sceneViewState":{"m_AlwaysRefresh":false,"showFog":true,"showSkybox":true,"showFlares":true,"showImageEffects":true,"showParticleSystems":true,"showVisualEffectGraphs":true,"m_FxEnabled":true},"in2DMode":false,"pivot":{"x":2.2632529735565187,"y":0.3761030435562134,"z":3.674961566925049},"rotation":{"x":0.1471436619758606,"y":-0.17264072597026826,"z":0.02609272301197052,"w":0.9735866189002991},"size":4.921615123748779,"orthographic":false}